dokkument/__init__.py
dokkument/browser_opener.py
dokkument/cli_display.py
dokkument/commands.py
dokkument/config_manager.py
dokkument/link_manager.py
dokkument/main.py
dokkument/parser.py
dokkument-1.0.0.dist-info/licenses/LICENSE
dokkument-1.0.0.dist-info/METADATA
dokkument-1.0.0.dist-info/WHEEL
dokkument-1.0.0.dist-info/entry_points.txt
dokkument-1.0.0.dist-info/top_level.txt
dokkument-1.0.0.dist-info/RECORD
