Metadata-Version: 2.4
Name: dokkument
Version: 1.0.0
Summary: CLI Manager for corporate documentation via .dokk files
Author-email: Roberto Zanolli <roberto.zanolli.2003@gmail.com>
Maintainer-email: Roberto Zanolli <roberto.zanolli.2003@gmail.com>
License-Expression: MIT
Project-URL: Homepage, https://github.com/RobertoZanolli/dokkument
Project-URL: Documentation, https://github.com/RobertoZanolli/dokkument#readme
Project-URL: Repository, https://github.com/RobertoZanolli/dokkument.git
Project-URL: Bug Tracker, https://github.com/RobertoZanolli/dokkument/issues
Project-URL: Changelog, https://github.com/RobertoZanolli/dokkument/blob/main/CHANGELOG.md
Keywords: cli,documentation,links,enterprise,tool,productivity
Classifier: Development Status :: 5 - Production/Stable
Classifier: Environment :: Console
Classifier: Intended Audience :: Developers
Classifier: Intended Audience :: System Administrators
Classifier: Operating System :: OS Independent
Classifier: Programming Language :: Python :: 3
Classifier: Programming Language :: Python :: 3.8
Classifier: Programming Language :: Python :: 3.9
Classifier: Programming Language :: Python :: 3.10
Classifier: Programming Language :: Python :: 3.11
Classifier: Programming Language :: Python :: 3.12
Classifier: Topic :: Documentation
Classifier: Topic :: Internet :: WWW/HTTP :: Browsers
Classifier: Topic :: Office/Business
Classifier: Topic :: Software Development :: Documentation
Classifier: Topic :: System :: Systems Administration
Classifier: Topic :: Utilities
Requires-Python: >=3.8
License-File: LICENSE
Provides-Extra: enhanced
Requires-Dist: rich>=10.0.0; extra == "enhanced"
Requires-Dist: click>=8.0.0; extra == "enhanced"
Requires-Dist: colorama>=0.4.4; extra == "enhanced"
Provides-Extra: dev
Requires-Dist: pytest>=7.0.0; extra == "dev"
Requires-Dist: pytest-cov>=4.0.0; extra == "dev"
Requires-Dist: pylint>=2.15.0; extra == "dev"
Requires-Dist: black>=22.0.0; extra == "dev"
Requires-Dist: isort>=5.0.0; extra == "dev"
Requires-Dist: flake8>=5.0.0; extra == "dev"
Requires-Dist: mypy>=1.0.0; extra == "dev"
Requires-Dist: pre-commit>=3.0.0; extra == "dev"
Provides-Extra: test
Requires-Dist: pytest>=7.0.0; extra == "test"
Requires-Dist: pytest-cov>=4.0.0; extra == "test"
Requires-Dist: pytest-mock>=3.10.0; extra == "test"
Requires-Dist: coverage[toml]>=6.0.0; extra == "test"
Provides-Extra: docs
Requires-Dist: sphinx>=5.0.0; extra == "docs"
Requires-Dist: sphinx-rtd-theme>=1.0.0; extra == "docs"
Requires-Dist: myst-parser>=0.18.0; extra == "docs"
Dynamic: license-file
